CHANGELOG.md
pangea_django/__init__.py
pangea_django/pangea_django_auth.py
pangea_django-1.0.1.dist-info/METADATA
pangea_django-1.0.1.dist-info/WHEEL
pangea_django-1.0.1.dist-info/RECORD
