Metadata-Version: 2.1
Name: pangea-django
Version: 1.0.1
Summary: Pangea Authentication Addon for Django
Home-page: https://github.com/pangeacyber/pangea-python
License: MIT
Keywords: Pangea,Django,AutnN
Author: Govind Salinas
Author-email: govind.salinas@pangea.cloud
Requires-Python: >=3.8.0,<4.0.0
Classifier: License :: OSI Approved :: MIT License
Classifier: Programming Language :: Python :: 3
Classifier: Programming Language :: Python :: 3.8
Classifier: Programming Language :: Python :: 3.9
Classifier: Programming Language :: Python :: 3.10
Classifier: Programming Language :: Python :: 3.11
Classifier: Programming Language :: Python :: 3.12
Classifier: Topic :: Software Development
Classifier: Topic :: Software Development :: Libraries
Requires-Dist: Django (>=4.2.11,<5.0.0)
Requires-Dist: pangea-sdk (>=3.7.1,<4.0.0)
Project-URL: Repository, https://github.com/pangeacyber/pangea-python
